PheTK/Cohort.py
PheTK/Demo.py
PheTK/PheWAS.py
PheTK/Phecode.py
PheTK/Plot.py
PheTK/__init__.py
PheTK/_paths.py
PheTK/_queries.py
PheTK/_utils.py
PheTK/phecode/phecode12.csv
PheTK/phecode/phecodeX.csv
PheTK/phecode/phecodeX_WHO.csv
PheTK-0.1.47.dist-info/LICENSE
PheTK-0.1.47.dist-info/METADATA
PheTK-0.1.47.dist-info/WHEEL
PheTK-0.1.47.dist-info/top_level.txt
PheTK-0.1.47.dist-info/RECORD
