Metadata-Version: 2.1
Name: PheTK
Version: 0.1.47
Summary: The Phenotype Toolkit
Home-page: https://github.com/nhgritctran/PheTK
Author: Tam Tran
Author-email: PheTK@mail.nih.gov
License: GPL-3.0
Requires-Python: >=3.7
License-File: LICENSE
Requires-Dist: adjusttext
Requires-Dist: connectorx
Requires-Dist: google-cloud-bigquery
Requires-Dist: hail
Requires-Dist: lifelines
Requires-Dist: lxml
Requires-Dist: matplotlib
Requires-Dist: numpy
Requires-Dist: pandas
Requires-Dist: polars
Requires-Dist: pyarrow
Requires-Dist: statsmodels
Requires-Dist: tqdm
